__init__.py
const.py
main.py
drkbloodbarometer-0.1.3.dist-info/licenses/LICENSE
drkbloodbarometer-0.1.3.dist-info/METADATA
drkbloodbarometer-0.1.3.dist-info/WHEEL
drkbloodbarometer-0.1.3.dist-info/top_level.txt
drkbloodbarometer-0.1.3.dist-info/RECORD
