Metadata-Version: 2.4
Name: drkbloodbarometer
Version: 0.1.3
Summary: A library for DRK blood donation service stock levels.
Requires-Python: >=3.12
License-File: LICENSE
Requires-Dist: beautifulsoup4>=4.13.3
Requires-Dist: requests>=2.32.3
Dynamic: license-file
